.gitignore
.pylintrc
.readthedocs.yml
AUTHORS.txt
LICENSE.txt
README.rst
pyproject.toml
setup.py
tox.ini
.github/workflows/sdist.yml
.github/workflows/tox.yml
doc/Makefile
doc/source/api.rst
doc/source/cli.rst
doc/source/conf.py
doc/source/examples.rst
doc/source/index.rst
doc/source/prov_patterns.rst
entity_management/__init__.py
entity_management/analysis.py
entity_management/atlas.py
entity_management/base.py
entity_management/config.py
entity_management/context.py
entity_management/core.py
entity_management/debug.py
entity_management/electrophysiology.py
entity_management/emodel.py
entity_management/exception.py
entity_management/experiment.py
entity_management/morphology.py
entity_management/nexus.py
entity_management/settings.py
entity_management/simulation.py
entity_management/state.py
entity_management/typecheck.py
entity_management/typing.py
entity_management/util.py
entity_management/workflow.py
entity_management.egg-info/PKG-INFO
entity_management.egg-info/SOURCES.txt
entity_management.egg-info/dependency_links.txt
entity_management.egg-info/entry_points.txt
entity_management.egg-info/requires.txt
entity_management.egg-info/top_level.txt
entity_management/circuit/__init__.py
entity_management/circuit/building/__init__.py
entity_management/circuit/building/functional.py
entity_management/cli/__init__.py
entity_management/cli/base.py
entity_management/cli/model_building_config.py
entity_management/data/type_to_schema_mapping.json
scripts/sync_type_mapping.py
tests/test_atlas.py
tests/test_base.py
tests/test_context.py
tests/test_core.py
tests/test_emodel.py
tests/test_kernel.py
tests/test_model_building_config.py
tests/test_morphology.py
tests/test_nexus.py
tests/test_simulation.py
tests/test_state.py
tests/test_typecheck.py
tests/test_util.py
tests/util.py
tests/data/atlas_release_resp.json
tests/data/cells_page1_resp.json
tests/data/cells_page2_resp.json
tests/data/detailed_circuit_resp.json
tests/data/emodel_configuration_resp.json
tests/data/emodel_data_catalog_resp.json
tests/data/emodel_pipeline_settings_resp.json
tests/data/emodel_release_resp.json
tests/data/emodel_resp.json
tests/data/emodel_script_resp.json
tests/data/emodel_workflow_resp.json
tests/data/entity_data_download_resp.json
