Metadata-Version: 2.1
Name: entity-management
Version: 1.6.0
Summary: Access to production entity management
Author: Blue Brain Project, EPFL
License: 
Project-URL: Homepage, https://github.com/BlueBrain/entity-management
Project-URL: Documentation, https://entity-management.readthedocs.io/en/stable/
Project-URL: Repository, https://github.com/BlueBrain/entity-management
Project-URL: Issues, https://github.com/BlueBrain/entity-management/issues
Keywords: computational neuroscience,simulation,analysis,nexus,parameters,BlueBrainProject
Classifier: Development Status :: 3 - Alpha
Classifier: Environment :: Console
Classifier: Operating System :: POSIX
Classifier: Topic :: Scientific/Engineering
Classifier: Topic :: Utilities
Requires-Python: >=3.8
License-File: LICENSE.txt
License-File: AUTHORS.txt
Requires-Dist: requests
Requires-Dist: attrs
Requires-Dist: python-dateutil
Requires-Dist: sparqlwrapper
Requires-Dist: rdflib
Requires-Dist: pyjwt
Requires-Dist: python-keycloak
Requires-Dist: click
Provides-Extra: docs
Requires-Dist: sphinx-bluebrain-theme; extra == "docs"
